logpipe/__init__.py
logpipe/abc.py
logpipe/admin.py
logpipe/apps.py
logpipe/constants.py
logpipe/consumer.py
logpipe/docgen_setup.py
logpipe/exceptions.py
logpipe/format.py
logpipe/models.py
logpipe/producer.py
logpipe/py.typed
logpipe/registry.py
logpipe/settings.py
logpipe/backend/__init__.py
logpipe/backend/dummy.py
logpipe/backend/kafka.py
logpipe/backend/kinesis.py
logpipe/formats/__init__.py
logpipe/formats/json.py
logpipe/formats/msgpack.py
logpipe/formats/pickle.py
logpipe/locale/es/LC_MESSAGES/django.mo
logpipe/locale/es/LC_MESSAGES/django.po
logpipe/management/__init__.py
logpipe/management/commands/__init__.py
logpipe/management/commands/run_kafka_consumer.py
logpipe/migrations/0001_initial.py
logpipe/migrations/0002_auto_20170427_1451.py
logpipe/migrations/0003_auto_20170427_1703.py
logpipe/migrations/0004_auto_20170502_1403.py
logpipe/migrations/0005_auto_20180917_1348.py
logpipe/migrations/0006_alter_kafkaoffset_options_and_more.py
logpipe/migrations/__init__.py
logpipe/tests/__init__.py
logpipe/tests/common.py
logpipe/tests/integration/__init__.py
logpipe/tests/integration/test_roundtrip.py
logpipe/tests/unit/__init__.py
logpipe/tests/unit/test_consumer.py
logpipe/tests/unit/test_format.py
logpipe/tests/unit/test_producer.py
logpipe/tests/unit/test_settings.py
logpipe/tests/unit/kafka/__init__.py
logpipe/tests/unit/kafka/test_consumer.py
logpipe/tests/unit/kafka/test_producer.py
logpipe/tests/unit/kinesis/__init__.py
logpipe/tests/unit/kinesis/test_consumer.py
logpipe/tests/unit/kinesis/test_producer.py
django_logpipe-1.5.1.dist-info/METADATA
django_logpipe-1.5.1.dist-info/WHEEL
django_logpipe-1.5.1.dist-info/licenses/LICENSE
django_logpipe-1.5.1.dist-info/RECORD
