Metadata-Version: 2.4
Name: django-logpipe
Version: 1.5.1
Summary: Move data around between Python services using Kafka and/or AWS Kinesis and Django Rest Framework serializers.
Project-URL: Homepage, https://gitlab.com/thelabnyc/django-logpipe
Project-URL: Repository, https://gitlab.com/thelabnyc/django-logpipe
Author-email: thelab <thelabdev@thelab.co>
License: ISC
License-File: LICENSE
Requires-Python: >=3.11
Requires-Dist: boto3<2,>=1.37.36
Requires-Dist: django>=4.2
Requires-Dist: djangorestframework>=3.16.0
Requires-Dist: kafka-python<3,>=2.1.5
Requires-Dist: lru-dict>=1.3.0
Requires-Dist: msgpack<2,>=1.1.0
Requires-Dist: pydantic<3,>=2.11.3
